systore/__init__.py
systore/cpu.py
systore/disk.py
systore/ram.py
systore-1.0.2.dist-info/LICENSE
systore-1.0.2.dist-info/METADATA
systore-1.0.2.dist-info/WHEEL
systore-1.0.2.dist-info/top_level.txt
systore-1.0.2.dist-info/RECORD
