Metadata-Version: 2.1
Name: systore
Version: 1.0.2
Summary: Get information about your system.
Author: Schkimansky
Author-email: <ahmadchawla1432@gmail.com>
Keywords: python,system,information,get information,get,get info,system info,get sys infoget system info
Classifier: Development Status :: 5 - Production/Stable
Classifier: Intended Audience :: Developers
Classifier: Programming Language :: Python :: 3
Classifier: Operating System :: Unix
Classifier: Operating System :: MacOS :: MacOS X
Classifier: Operating System :: Microsoft :: Windows
License-File: LICENSE
Requires-Dist: psutil
